outpost/__init__.py
outpost/main.py
outpost/utils.py
outpost/images/Outpost24-logo.ico
outpost/images/Outpost24-logo.png
outposttools-1.5.3.dist-info/LICENSE
outposttools-1.5.3.dist-info/METADATA
outposttools-1.5.3.dist-info/WHEEL
outposttools-1.5.3.dist-info/entry_points.txt
outposttools-1.5.3.dist-info/top_level.txt
outposttools-1.5.3.dist-info/RECORD
