Metadata-Version: 2.1
Name: outposttools
Version: 1.5.3
License-File: LICENSE
Requires-Dist: requests
Requires-Dist: tk
Requires-Dist: pillow
